{"/*":["X-Frame-Options: DENY","X-XSS-Protection: 1; mode=block","X-Content-Type-Options: nosniff","Referrer-Policy: same-origin"],"/styles.9f7dc1a96bd2b86d8b4e.css":["Cache-Control: public, max-age=31536000, immutable"],"/commons-cce47f30aab8a6c088d8.js":["Cache-Control: public, max-age=31536000, immutable"],"/5b7106d8783398d5c123601c65f15bbaf887e6d5-339d17136bec1a132d49.js":["Cache-Control: public, max-age=31536000, immutable"],"/component---src-pages-asteroid-shooter-js-513291246615e6b89943.js":["Cache-Control: public, max-age=31536000, immutable"],"/component---src-pages-booking-system-js-5d606147913b334376a1.js":["Cache-Control: public, max-age=31536000, immutable"],"/component---src-pages-busy-backpack-js-a974fae7ea8079b7aca4.js":["Cache-Control: public, max-age=31536000, immutable"],"/component---src-pages-index-js-009626b35b272f5e3d48.js":["Cache-Control: public, max-age=31536000, immutable"],"/component---src-pages-mobile-app-js-e8965e73dff9d221d09d.js":["Cache-Control: public, max-age=31536000, immutable"],"/component---src-pages-pencil-puzzle-js-7bc7307b333f7e88faac.js":["Cache-Control: public, max-age=31536000, immutable"],"/component---src-pages-undergraduate-computing-project-js-cb07769bc074b46d4571.js":["Cache-Control: public, max-age=31536000, immutable"],"/component---src-pages-unity-projects-js-982b40e011cc7a1d7ec0.js":["Cache-Control: public, max-age=31536000, immutable"],"/component---src-pages-use-state-js-ea0168661663bcb33943.js":["Cache-Control: public, max-age=31536000, immutable"],"/component---src-pages-wai-js-14b27aef5883c9e002ee.js":["Cache-Control: public, max-age=31536000, immutable"],"/webpack-runtime-26b361646c228ab2c681.js":["Cache-Control: public, max-age=31536000, immutable"],"/framework-65ceedd5e3bb862b2b6b.js":["Cache-Control: public, max-age=31536000, immutable"],"/app-150c8572cd179132051d.js":["Cache-Control: public, max-age=31536000, immutable"],"/static/*":["Cache-Control: public, max-age=31536000, immutable"],"/sw.js":["Cache-Control: public, max-age=0, must-revalidate"],"/asteroid-shooter/":["Link: </webpack-runtime-26b361646c228ab2c681.js>; rel=preload; as=script; nopush","Link: </framework-65ceedd5e3bb862b2b6b.js>; rel=preload; as=script; nopush","Link: </app-150c8572cd179132051d.js>; rel=preload; as=script; nopush","Link: </commons-cce47f30aab8a6c088d8.js>; rel=preload; as=script; nopush","Link: </5b7106d8783398d5c123601c65f15bbaf887e6d5-339d17136bec1a132d49.js>; rel=preload; as=script; nopush","Link: </component---src-pages-asteroid-shooter-js-513291246615e6b89943.js>; rel=preload; as=script; nopush","Link: </page-data/app-data.json>; rel=preload; as=fetch; crossorigin; nopush","Link: </page-data/asteroid-shooter/page-data.json>; rel=preload; as=fetch; crossorigin; nopush"],"/booking-system/":["Link: </webpack-runtime-26b361646c228ab2c681.js>; rel=preload; as=script; nopush","Link: </framework-65ceedd5e3bb862b2b6b.js>; rel=preload; as=script; nopush","Link: </app-150c8572cd179132051d.js>; rel=preload; as=script; nopush","Link: </commons-cce47f30aab8a6c088d8.js>; rel=preload; as=script; nopush","Link: </5b7106d8783398d5c123601c65f15bbaf887e6d5-339d17136bec1a132d49.js>; rel=preload; as=script; nopush","Link: </component---src-pages-booking-system-js-5d606147913b334376a1.js>; rel=preload; as=script; nopush","Link: </page-data/app-data.json>; rel=preload; as=fetch; crossorigin; nopush","Link: </page-data/booking-system/page-data.json>; rel=preload; as=fetch; crossorigin; nopush"],"/busy-backpack/":["Link: </webpack-runtime-26b361646c228ab2c681.js>; rel=preload; as=script; nopush","Link: </framework-65ceedd5e3bb862b2b6b.js>; rel=preload; as=script; nopush","Link: </app-150c8572cd179132051d.js>; rel=preload; as=script; nopush","Link: </commons-cce47f30aab8a6c088d8.js>; rel=preload; as=script; nopush","Link: </5b7106d8783398d5c123601c65f15bbaf887e6d5-339d17136bec1a132d49.js>; rel=preload; as=script; nopush","Link: </component---src-pages-busy-backpack-js-a974fae7ea8079b7aca4.js>; rel=preload; as=script; nopush","Link: </page-data/app-data.json>; rel=preload; as=fetch; crossorigin; nopush","Link: </page-data/busy-backpack/page-data.json>; rel=preload; as=fetch; crossorigin; nopush"],"/":["Link: </webpack-runtime-26b361646c228ab2c681.js>; rel=preload; as=script; nopush","Link: </framework-65ceedd5e3bb862b2b6b.js>; rel=preload; as=script; nopush","Link: </app-150c8572cd179132051d.js>; rel=preload; as=script; nopush","Link: </commons-cce47f30aab8a6c088d8.js>; rel=preload; as=script; nopush","Link: </5b7106d8783398d5c123601c65f15bbaf887e6d5-339d17136bec1a132d49.js>; rel=preload; as=script; nopush","Link: </component---src-pages-index-js-009626b35b272f5e3d48.js>; rel=preload; as=script; nopush","Link: </page-data/app-data.json>; rel=preload; as=fetch; crossorigin; nopush","Link: </page-data/index/page-data.json>; rel=preload; as=fetch; crossorigin; nopush"],"/mobile-app/":["Link: </webpack-runtime-26b361646c228ab2c681.js>; rel=preload; as=script; nopush","Link: </framework-65ceedd5e3bb862b2b6b.js>; rel=preload; as=script; nopush","Link: </app-150c8572cd179132051d.js>; rel=preload; as=script; nopush","Link: </commons-cce47f30aab8a6c088d8.js>; rel=preload; as=script; nopush","Link: </5b7106d8783398d5c123601c65f15bbaf887e6d5-339d17136bec1a132d49.js>; rel=preload; as=script; nopush","Link: </component---src-pages-mobile-app-js-e8965e73dff9d221d09d.js>; rel=preload; as=script; nopush","Link: </page-data/app-data.json>; rel=preload; as=fetch; crossorigin; nopush","Link: </page-data/mobile-app/page-data.json>; rel=preload; as=fetch; crossorigin; nopush"],"/pencil-puzzle/":["Link: </webpack-runtime-26b361646c228ab2c681.js>; rel=preload; as=script; nopush","Link: </framework-65ceedd5e3bb862b2b6b.js>; rel=preload; as=script; nopush","Link: </app-150c8572cd179132051d.js>; rel=preload; as=script; nopush","Link: </commons-cce47f30aab8a6c088d8.js>; rel=preload; as=script; nopush","Link: </5b7106d8783398d5c123601c65f15bbaf887e6d5-339d17136bec1a132d49.js>; rel=preload; as=script; nopush","Link: </component---src-pages-pencil-puzzle-js-7bc7307b333f7e88faac.js>; rel=preload; as=script; nopush","Link: </page-data/app-data.json>; rel=preload; as=fetch; crossorigin; nopush","Link: </page-data/pencil-puzzle/page-data.json>; rel=preload; as=fetch; crossorigin; nopush"],"/undergraduate-computing-project/":["Link: </webpack-runtime-26b361646c228ab2c681.js>; rel=preload; as=script; nopush","Link: </framework-65ceedd5e3bb862b2b6b.js>; rel=preload; as=script; nopush","Link: </app-150c8572cd179132051d.js>; rel=preload; as=script; nopush","Link: </commons-cce47f30aab8a6c088d8.js>; rel=preload; as=script; nopush","Link: </5b7106d8783398d5c123601c65f15bbaf887e6d5-339d17136bec1a132d49.js>; rel=preload; as=script; nopush","Link: </component---src-pages-undergraduate-computing-project-js-cb07769bc074b46d4571.js>; rel=preload; as=script; nopush","Link: </page-data/app-data.json>; rel=preload; as=fetch; crossorigin; nopush","Link: </page-data/undergraduate-computing-project/page-data.json>; rel=preload; as=fetch; crossorigin; nopush"],"/unity-projects/":["Link: </webpack-runtime-26b361646c228ab2c681.js>; rel=preload; as=script; nopush","Link: </framework-65ceedd5e3bb862b2b6b.js>; rel=preload; as=script; nopush","Link: </app-150c8572cd179132051d.js>; rel=preload; as=script; nopush","Link: </commons-cce47f30aab8a6c088d8.js>; rel=preload; as=script; nopush","Link: </5b7106d8783398d5c123601c65f15bbaf887e6d5-339d17136bec1a132d49.js>; rel=preload; as=script; nopush","Link: </component---src-pages-unity-projects-js-982b40e011cc7a1d7ec0.js>; rel=preload; as=script; nopush","Link: </page-data/app-data.json>; rel=preload; as=fetch; crossorigin; nopush","Link: </page-data/unity-projects/page-data.json>; rel=preload; as=fetch; crossorigin; nopush"],"/useState/":["Link: </webpack-runtime-26b361646c228ab2c681.js>; rel=preload; as=script; nopush","Link: </framework-65ceedd5e3bb862b2b6b.js>; rel=preload; as=script; nopush","Link: </app-150c8572cd179132051d.js>; rel=preload; as=script; nopush","Link: </commons-cce47f30aab8a6c088d8.js>; rel=preload; as=script; nopush","Link: </component---src-pages-use-state-js-ea0168661663bcb33943.js>; rel=preload; as=script; nopush","Link: </page-data/app-data.json>; rel=preload; as=fetch; crossorigin; nopush","Link: </page-data/useState/page-data.json>; rel=preload; as=fetch; crossorigin; nopush"],"/wai/":["Link: </webpack-runtime-26b361646c228ab2c681.js>; rel=preload; as=script; nopush","Link: </framework-65ceedd5e3bb862b2b6b.js>; rel=preload; as=script; nopush","Link: </app-150c8572cd179132051d.js>; rel=preload; as=script; nopush","Link: </commons-cce47f30aab8a6c088d8.js>; rel=preload; as=script; nopush","Link: </5b7106d8783398d5c123601c65f15bbaf887e6d5-339d17136bec1a132d49.js>; rel=preload; as=script; nopush","Link: </component---src-pages-wai-js-14b27aef5883c9e002ee.js>; rel=preload; as=script; nopush","Link: </page-data/app-data.json>; rel=preload; as=fetch; crossorigin; nopush","Link: </page-data/wai/page-data.json>; rel=preload; as=fetch; crossorigin; nopush"]}